mydbs/__init__.py
mydbs/dbmysql.py
mydbs/dbsqlite.py
mydbs-0.1.5.dist-info/LICENSE
mydbs-0.1.5.dist-info/METADATA
mydbs-0.1.5.dist-info/WHEEL
mydbs-0.1.5.dist-info/top_level.txt
mydbs-0.1.5.dist-info/RECORD
