Metadata-Version: 2.1
Name: mydbs
Version: 0.1.5
Summary: databases operations without sqls
Home-page: https://mehralsaugen.github.io/
Author: shockwave
Author-email: yao_yingzhe@163.com
License: MIT
Platform: UNKNOWN
